yts_downloader/__init__.py
yts_downloader/yts_downloader.py
yts_downloader-0.1.2.dist-info/LICENSE
yts_downloader-0.1.2.dist-info/METADATA
yts_downloader-0.1.2.dist-info/WHEEL
yts_downloader-0.1.2.dist-info/entry_points.txt
yts_downloader-0.1.2.dist-info/top_level.txt
yts_downloader-0.1.2.dist-info/RECORD
