Metadata-Version: 2.1
Name: yts-downloader
Version: 0.1.2
Summary: A simple python CLI to download movies from yts or formerly yify
Home-page: https://github.com/FlashBlaze/yts-downloader/
Author: Neeraj Lagwankar
Author-email: neerajlagwankar@gmail.com
License: MIT license
Keywords: yts_downloader yts torrent download
Platform: UNKNOWN
Classifier: Development Status :: 2 - Pre-Alpha
Classifier: Intended Audience :: Developers
Classifier: License :: OSI Approved :: MIT License
Classifier: Natural Language :: English
Classifier: Programming Language :: Python :: 3.4
Classifier: Programming Language :: Python :: 3.5
Classifier: Programming Language :: Python :: 3.6
Classifier: Programming Language :: Python :: 3.7
Requires-Dist: requests
Requires-Dist: beautifulsoup4
